cyb600_lab1_perreaua10/__init__.py
cyb600_lab1_perreaua10/main.py
cyb600_lab1_perreaua10-1.1.0.data/scripts/start-web-server
cyb600_lab1_perreaua10-1.1.0.dist-info/LICENSE
cyb600_lab1_perreaua10-1.1.0.dist-info/METADATA
cyb600_lab1_perreaua10-1.1.0.dist-info/WHEEL
cyb600_lab1_perreaua10-1.1.0.dist-info/top_level.txt
cyb600_lab1_perreaua10-1.1.0.dist-info/RECORD
