Metadata-Version: 2.1
Name: cyb600-lab1-perreaua10
Version: 1.1.0
Author: Andrew Perreault
Author-email: perreaua@canisius.edu
License: Apache License Version 2.0
License-File: LICENSE
Requires-Dist: fastapi
Requires-Dist: uvicorn
